odoo10_addon_l10n_ec_config-10.0.1.0.0.99.dev3-py2.7-nspkg.pth
odoo/addons/l10n_ec_config/README.rst
odoo/addons/l10n_ec_config/__init__.py
odoo/addons/l10n_ec_config/__manifest__.py
odoo/addons/l10n_ec_config/i18n/l10n_ec_config.pot
odoo/addons/l10n_ec_config/models/__init__.py
odoo/addons/l10n_ec_config/models/res_config.py
odoo/addons/l10n_ec_config/static/description/icon.png
odoo/addons/l10n_ec_config/views/res_config.xml
odoo10_addon_l10n_ec_config-10.0.1.0.0.99.dev3.dist-info/METADATA
odoo10_addon_l10n_ec_config-10.0.1.0.0.99.dev3.dist-info/RECORD
odoo10_addon_l10n_ec_config-10.0.1.0.0.99.dev3.dist-info/WHEEL
odoo10_addon_l10n_ec_config-10.0.1.0.0.99.dev3.dist-info/namespace_packages.txt
odoo10_addon_l10n_ec_config-10.0.1.0.0.99.dev3.dist-info/top_level.txt
