Metadata-Version: 2.1
Name: odoo10-addon-l10n-ec-config
Version: 10.0.1.0.0.99.dev3
Summary: Ecuador's localization config settings
Home-page: http://www.libre.ec/
Author: Fabrica de Software Libre,Odoo Community Association (OCA)
Author-email: support@odoo-community.org
License: AGPL-3
Platform: UNKNOWN
Classifier: Programming Language :: Python
Classifier: Framework :: Odoo
Classifier: License :: OSI Approved :: GNU Affero General Public License v3
Requires-Python: ~=2.7
Requires-Dist: odoo (<10.1dev,>=10.0)
